prandom.v
module Prandom(clk,rst,Q);
input clk;
input rst;
output [2:0] Q;
reg [2:0] Q;

 always@(posedge clk)
  begin
  if(rst)begin
    Q<=3'b110;
  end
  else
   begin
    Q[2]<=Q[1];
    Q[1]<=Q[0];
    Q[0]<=Q[2]^Q[0];
      end
    end
  endmodule

prandom_tb.v
`timescale 1ns/1ps
module  Prandom_tb();
reg clk;
reg rst;
wire[2:0] Q;

  parameter PERIOD  = 20;
  parameter real DUTY_CYCLE  = 0.5;
  parameter OFFSET  = 0;
  initial
  begin
      #OFFSET;
      forever
      begin
        clk = 1'b1;
        #(PERIOD-(PERIOD*DUTY_CYCLE))
        clk = 1'b0;
        #(PERIOD*DUTY_CYCLE);
        end
      end
    initial begin
          rst = 1;
      #5 rst = 0;
      #250 $finish;
    end
    initial
    begin
          $dumpfile("Prandom.vcd");
          $dumpvars(0,Prandom_tb);
    end
    Prandom Prandom_tb( .clk(clk), .rst(rst), .Q(Q));
    endmodule

Prandom.vcd
$date
	Tue May 17 22:52:17 2022
$end
$version
	Icarus Verilog
$end
$timescale
	1ps
$end
$scope module Prandom_tb $end
$scope module Prandom_tb $end
$var wire 1 ! clk $end
$var wire 1 " rst $end
$var reg 3 # Q [2:0] $end
$upscope $end
$upscope $end
$enddefinitions $end
#0
$dumpvars
b110 #
1"
1!
$end
#5000
0"
#10000
0!
#20000
b101 #
1!
#30000
0!
#40000
b10 #
1!
#50000
0!
#60000
b100 #
1!
#70000
0!
#80000
b1 #
1!
#90000
0!
#100000
b11 #
1!
#110000
0!
#120000
b111 #
1!
#130000
0!
#140000
b110 #
1!
#150000
0!
#160000
b101 #
1!
#170000
0!
#180000
b10 #
1!
#190000
0!
#200000
b100 #
1!
#210000
0!
#220000
b1 #
1!
#230000
0!
#240000
b11 #
1!
